django_samesite_none/__init__.py
django_samesite_none/middleware.py
django_samesite_none-0.0.3.dist-info/METADATA
django_samesite_none-0.0.3.dist-info/WHEEL
django_samesite_none-0.0.3.dist-info/top_level.txt
django_samesite_none-0.0.3.dist-info/RECORD
