Metadata-Version: 2.1
Name: django-samesite-none
Version: 0.0.3
Summary: Django middleware which sets SameSite flag to 'None' for cookies where it is None
Home-page: https://github.com/zvyn/django-samesite-none
Author: Milan Oberkirch
Author-email: milan.oberkirch@geops.de
License: UNKNOWN
Keywords: django-samesite-none
Platform: UNKNOWN
Classifier: Framework :: Django :: 2.2
Classifier: Intended Audience :: Developers
Classifier: Natural Language :: English
Classifier: Programming Language :: Python :: 3
Classifier: Programming Language :: Python :: 3.5
Classifier: Programming Language :: Python :: 3.6
Classifier: Programming Language :: Python :: 3.7
Classifier: Programming Language :: Python :: 3.8
